{
    "64bit-SizeT": false,
    "64bit-ValueT": false,
    "64bit-VertexT": false,
    "advance-mode": "LB_CULL",
    "average-duty": 0.0,
    "avg-mteps": 14519.011227457142,
    "avg-process-time": 17.960119247436525,
    "binary-prefix": "",
    "command-line": "../../../build/bin/bfs rmat --graph-scale=24 --graph-edgefactor=16 --num-runs=10 --quick --device=0 --src=random --64bit-SizeT=false --64bit-VertexT=false --idempotence=true --mark-pred=false --direction-optimized=true --advance-mode=LB_CULL --tag=dobfs_parameter_sweep --queue-factor=6.5 --undirected=true --do-a=0.005 --do-b=0.0005 --jsondir=./DOBFS/rmat_n24_e16",
    "communicate-latency": 0,
    "communicate-multipy": 1.0,
    "compiler": "Gnu GCC C/C++",
    "compiler-version": 70500000,
    "dataset": "rmat_n24_e16.000000",
    "device": 0,
    "direction-optimized": true,
    "do-a": 0.004999999888241291,
    "do-b": 0.0005000000237487257,
    "edge-value-min": 0.0,
    "edge-value-range": 64.0,
    "edge-value-seed": 0,
    "edges-queued": 0,
    "edges-redundance": 0.0,
    "edges-visited": 260763173,
    "engine": "Gunrock",
    "expand-latency": 0,
    "filter-mode": "CULL",
    "filtered-process-times": [
        22.465944290161134,
        19.465923309326173,
        6.739139556884766,
        32.156944274902347,
        11.481046676635743,
        14.667987823486329,
        9.66501235961914,
        32.11212158203125,
        25.062084197998048,
        5.7849884033203129
    ],
    "filtered-srcs": [
        4220612,
        474634,
        9794440,
        3646536,
        3740072,
        3195929,
        10302497,
        11566163,
        11604020,
        5929819
    ],
    "fullqueue-latency": 0,
    "git-commit-sha": "06fafd77b39c0c02a7f1bf1945296c650538e1c3",
    "gpuinfo": {
        "name": "Quadro GV100",
        "total_global_mem": 34087305216,
        "major": "7",
        "minor": "0",
        "clock_rate": 1627000,
        "multi_processor_count": 80,
        "driver_api": "10020",
        "driver_version": "10020",
        "runtime_version": "10020",
        "compute_version": "70"
    },
    "graph-edgefactor": 16.0,
    "graph-edges": 49152,
    "graph-file": "",
    "graph-nodes": 1024,
    "graph-scale": 24,
    "graph-seed": 0,
    "graph-type": "rmat",
    "grmat": false,
    "gunrock-version": "1.1.0",
    "help": false,
    "idempotence": true,
    "json": false,
    "json-schema": "2019-09-20",
    "jsondir": "./DOBFS/rmat_n24_e16",
    "jsonfile": "",
    "load-time": 138689.0,
    "makeout-latency": 0,
    "mark-pred": false,
    "max-grid-size": 0,
    "max-mteps": 45075.83331547115,
    "max-process-time": 32.156944274902347,
    "min-mteps": 8109.078112982235,
    "min-process-time": 5.7849884033203129,
    "nodes-queued": 43035768,
    "nodes-redundance": 463.62286936087608,
    "nodes-visited": 7635561,
    "num-edges": 262984689,
    "num-runs": 10,
    "num-vertices": 16777216,
    "partition-factor": 0.5,
    "partition-method": "random",
    "partition-seed": 0,
    "postprocess-time": 3006.7150592803957,
    "preprocess-time": 1172.15,
    "primitive": "BFS",
    "process-times": [
        22.465944290161134,
        19.465923309326173,
        6.739139556884766,
        32.156944274902347,
        11.481046676635743,
        14.667987823486329,
        9.66501235961914,
        32.11212158203125,
        25.062084197998048,
        5.7849884033203129
    ],
    "queue-factor": 6.5,
    "quick": true,
    "quiet": false,
    "random-edge-values": false,
    "read-from-binary": true,
    "remove-duplicate-edges": true,
    "remove-self-loops": true,
    "rgg-thfactor": 0.55,
    "rgg-threshold": 0.0,
    "rmat-a": 0.57,
    "rmat-b": 0.19,
    "rmat-c": 0.19,
    "rmat-d": 0.05,
    "search-depth": 8,
    "size-check": true,
    "small-world-k": 6,
    "small-world-p": 0.0,
    "sort-csr": false,
    "src": "random",
    "src-seed": 1590819465,
    "srcs": [
        4220612,
        474634,
        9794440,
        3646536,
        3740072,
        3195929,
        10302497,
        11566163,
        11604020,
        5929819
    ],
    "stddev-degree": 248.68272399902345,
    "stddev-process-time": 9.330628743787904,
    "store-to-binary": true,
    "subqueue-latency": 0,
    "sysinfo": {
        "sysname": "Linux",
        "release": "5.3.0-46-generic",
        "version": "#38~18.04.1-Ubuntu SMP Tue Mar 31 04:17:56 UTC 2020",
        "machine": "x86_64",
        "nodename": "bowser"
    },
    "tag": [
        "dobfs_parameter_sweep"
    ],
    "time": "Fri May 29 23:17:45 2020\n",
    "total-time": 4360.173940658569,
    "trans-factor": 1.0,
    "undirected": true,
    "userinfo": {
        "login": "mosama"
    },
    "v": false,
    "validation": "last",
    "vertex-start-from-zero": true
}