{
    "64bit_SizeT" : false,
    "64bit_Value" : false,
    "64bit_VertexId" : false,
    "algorithm" : "BFS",
    "alpha" : 6,
    "average_duty" : 0,
    "beta" : 6,
    "command_line" : "./bin/test_bfs_8.0_x86_64 grmat --rmat_scale=23 --rmat_edgefactor=32 --src=randomize2 --queue-sizing=6.5 --in-sizing=4 --iteration-num=64 --tag=do_sweep2 --undirected --idempotence --direction-optimized --traversal-mode=LB_CULL --device=0 --do_a=0.2 --do_b=0.0005 --jsondir=./eval/CentOS7.2_k40cx1",
    "communicate_latency" : 0,
    "communicate_multipy" : -1,
    "compensate" : false,
    "compiler" : "Gnu GCC C/C++",
    "compiler_version" : 40800005,
    "dataset" : "rmat_n23_e32",
    "debug_mode" : false,
    "delta" : 0.85000002384185791,
    "delta_factor" : 16,
    "destination_vertex" : 8388607,
    "device_list" : [
        0
    ],
    "direction_optimized" : true,
    "do_a" : 0.20000000298023224,
    "do_b" : 0.00050000002374872565,
    "duplicate_graph" : false,
    "edge_value" : false,
    "edges_queued" : 313431862,
    "edges_redundance" : 0,
    "edges_visited" : 506828132,
    "elapsed" : 26.129785537719727,
    "engine" : "Gunrock",
    "error" : 0.0099999997764825821,
    "expand_latency" : 0,
    "fullqueue_latency" : 0,
    "git_commit_sha1" : "6b7b3e5fddb95feda52dfa83992c51a8e4c14663",
    "gpuinfo" : {
        "clock_rate" : 745000,
        "compute_version" : 35,
        "driver_api" : 8000,
        "driver_version" : 8000,
        "major" : 3,
        "minor" : 5,
        "multi_processor_count" : 15,
        "name" : "Tesla K40m",
        "runtime_version" : 8000,
        "total_global_mem" : 11995578368
    },
    "graph_type" : "grmat",
    "gunrock_version" : "0.4.0",
    "idempotent" : true,
    "instrument" : false,
    "json" : false,
    "jsondir" : "./eval/CentOS7.2_k40cx1",
    "jsonfile" : "",
    "label" : "",
    "load_time" : 22015.098094940186,
    "m_teps" : 19396.56640625,
    "makeout_latency" : 0,
    "mark_predecessors" : false,
    "max_grid_size" : 0,
    "max_in_sizing" : 4,
    "max_iteration" : 50,
    "max_process_time" : 55.602073669433594,
    "max_queue_sizing" : 6.5,
    "max_queue_sizing1" : -1,
    "min_process_time" : 9.0160369873046875,
    "multi_graphs" : false,
    "node_value" : false,
    "nodes_queued" : 9744664,
    "nodes_redundance" : 82.047124649133877,
    "nodes_visited" : 5352825,
    "normalized" : false,
    "num_edges" : 506829356,
    "num_gpus" : 1,
    "num_iteration" : 64,
    "num_vertices" : 8388608,
    "output_filename" : "",
    "partition_factor" : -1,
    "partition_method" : "random",
    "partition_seed" : -1,
    "postprocess_time" : 45.353174209594727,
    "preprocess_time" : 2575.8180618286133,
    "process_times" : [
        36.824941635131836,
        55.602073669433594,
        12.032032012939453,
        16.280889511108398,
        10.784149169921875,
        14.374017715454102,
        10.855197906494141,
        27.670860290527344,
        23.499965667724609,
        31.976938247680664,
        12.083053588867188,
        12.032985687255859,
        23.340940475463867,
        20.196914672851562,
        42.140007019042969,
        46.332120895385742,
        16.479969024658203,
        14.613866806030273,
        9.3998908996582031,
        41.018009185791016,
        36.721944808959961,
        12.278079986572266,
        52.07514762878418,
        54.615974426269531,
        35.61711311340332,
        44.500827789306641,
        50.240039825439453,
        31.814098358154297,
        53.223848342895508,
        47.635078430175781,
        25.825977325439453,
        23.397207260131836,
        12.103080749511719,
        23.304939270019531,
        23.982048034667969,
        24.889945983886719,
        10.403156280517578,
        17.979145050048828,
        16.432046890258789,
        52.147150039672852,
        23.461103439331055,
        47.166109085083008,
        9.2899799346923828,
        50.289154052734375,
        40.740013122558594,
        10.607004165649414,
        9.0160369873046875,
        9.2179775238037109,
        16.191959381103516,
        10.605096817016602,
        10.403156280517578,
        12.418985366821289,
        9.2389583587646484,
        49.64900016784668,
        9.2420578002929688,
        52.862882614135742,
        24.837017059326172,
        10.596036911010742,
        9.2449188232421875,
        9.6390247344970703,
        12.178897857666016,
        49.718141555786133,
        9.5970630645751953,
        49.370050430297852
    ],
    "quick_mode" : false,
    "quiet_mode" : false,
    "random_edge_value" : false,
    "ref_filename" : "",
    "rmat_a" : 0.56999999999999995,
    "rmat_b" : 0.19,
    "rmat_c" : 0.19,
    "rmat_d" : 0.050000000000000044,
    "rmat_edgefactor" : 32,
    "rmat_edges" : 268435456,
    "rmat_nodes" : 8388608,
    "rmat_scale" : 23,
    "rmat_seed" : -1,
    "rmat_vmin" : 1,
    "rmat_vmultipiler" : 64,
    "scaled" : false,
    "search_depth" : 7,
    "size_check" : true,
    "source_list" : [
    ],
    "source_seed" : -1,
    "source_type" : "random2",
    "source_vertex" : 0,
    "stream_from_host" : false,
    "subqueue_latency" : 0,
    "sysinfo" : {
        "machine" : "x86_64",
        "nodename" : "ivb124",
        "release" : "3.10.0-327.18.2.el7.x86_64",
        "sysname" : "Linux",
        "version" : "#1 SMP Thu May 12 11:03:55 UTC 2016"
    },
    "tag" : "do_sweep2",
    "time" : "Wed Nov 30 07:36:08 2016\n",
    "top_nodes" : 0,
    "total_time" : 28660.789012908936,
    "traversal_mode" : "LB_CULL",
    "undirected" : true,
    "userinfo" : {
        "login" : "ypan"
    },
    "write_time" : 0
}