{
    "64bit_SizeT" : false,
    "64bit_Value" : false,
    "64bit_VertexId" : false,
    "algorithm" : "BFS",
    "alpha" : 6,
    "average_duty" : 0,
    "beta" : 6,
    "command_line" : "./bin/test_bfs_8.0_x86_64 market ../../dataset/large/hollywood-2009/hollywood-2009.mtx --src=randomize2 --queue-sizing=6.5 --in-sizing=4 --iteration-num=64 --tag=do_sweep2 --undirected --idempotence --direction-optimized --traversal-mode=LB_CULL --device=0 --do_a=1000 --do_b=500 --jsondir=./eval/CentOS7.2_k40cx1",
    "communicate_latency" : 0,
    "communicate_multipy" : -1,
    "compensate" : false,
    "compiler" : "Gnu GCC C/C++",
    "compiler_version" : 40800005,
    "dataset" : "hollywood-2009",
    "debug_mode" : false,
    "delta" : 0.85000002384185791,
    "delta_factor" : 16,
    "destination_vertex" : 1139904,
    "device_list" : [
        0
    ],
    "direction_optimized" : true,
    "do_a" : 1000,
    "do_b" : 500,
    "duplicate_graph" : false,
    "edge_value" : false,
    "edges_queued" : 117338305,
    "edges_redundance" : 4.1957732774491143,
    "edges_visited" : 112613306,
    "elapsed" : 18.348920822143555,
    "engine" : "Gunrock",
    "error" : 0.0099999997764825821,
    "expand_latency" : 0,
    "fullqueue_latency" : 0,
    "git_commit_sha1" : "6b7b3e5fddb95feda52dfa83992c51a8e4c14663",
    "gpuinfo" : {
        "clock_rate" : 745000,
        "compute_version" : 35,
        "driver_api" : 8000,
        "driver_version" : 8000,
        "major" : 3,
        "minor" : 5,
        "multi_processor_count" : 15,
        "name" : "Tesla K40m",
        "runtime_version" : 8000,
        "total_global_mem" : 11995578368
    },
    "graph_type" : "market",
    "gunrock_version" : "0.4.0",
    "idempotent" : true,
    "instrument" : false,
    "json" : false,
    "jsondir" : "./eval/CentOS7.2_k40cx1",
    "jsonfile" : "",
    "label" : "",
    "load_time" : 1036.9460582733154,
    "m_teps" : 6137.32568359375,
    "makeout_latency" : 0,
    "mark_predecessors" : false,
    "max_grid_size" : 0,
    "max_in_sizing" : 4,
    "max_iteration" : 50,
    "max_process_time" : 20.090103149414062,
    "max_queue_sizing" : 6.5,
    "max_queue_sizing1" : -1,
    "min_process_time" : 0.21290779113769531,
    "multi_graphs" : false,
    "node_value" : false,
    "nodes_queued" : 1081393,
    "nodes_redundance" : 1.1473858085950579,
    "nodes_visited" : 1069126,
    "normalized" : false,
    "num_edges" : 112751422,
    "num_gpus" : 1,
    "num_iteration" : 64,
    "num_vertices" : 1139905,
    "output_filename" : "",
    "partition_factor" : -1,
    "partition_method" : "random",
    "partition_seed" : -1,
    "postprocess_time" : 9.98687744140625,
    "preprocess_time" : 597.89299964904785,
    "process_times" : [
        19.479990005493164,
        18.815994262695312,
        18.681049346923828,
        18.666982650756836,
        18.440008163452148,
        19.043922424316406,
        20.090103149414062,
        19.431114196777344,
        18.793821334838867,
        19.075155258178711,
        18.476009368896484,
        18.496990203857422,
        18.362998962402344,
        18.474102020263672,
        18.559932708740234,
        18.583059310913086,
        18.862009048461914,
        18.796920776367188,
        18.321990966796875,
        18.440008163452148,
        18.365144729614258,
        18.561124801635742,
        18.971920013427734,
        18.409967422485352,
        18.651008605957031,
        18.347978591918945,
        18.438100814819336,
        18.371820449829102,
        18.778085708618164,
        18.381118774414062,
        18.701076507568359,
        18.759965896606445,
        18.729925155639648,
        18.579006195068359,
        18.996953964233398,
        18.563985824584961,
        18.726110458374023,
        18.332958221435547,
        18.836021423339844,
        18.234968185424805,
        18.455028533935547,
        18.685102462768555,
        0.21290779113769531,
        18.48912239074707,
        19.026041030883789,
        18.483161926269531,
        18.435955047607422,
        18.19920539855957,
        18.36705207824707,
        18.404006958007812,
        18.453836441040039,
        18.808126449584961,
        18.401145935058594,
        18.517017364501953,
        18.518924713134766,
        18.641948699951172,
        18.306970596313477,
        18.539905548095703,
        18.121957778930664,
        19.553184509277344,
        18.96214485168457,
        18.198966979980469,
        18.657922744750977,
        18.261909484863281
    ],
    "quick_mode" : false,
    "quiet_mode" : false,
    "random_edge_value" : false,
    "ref_filename" : "",
    "scaled" : false,
    "search_depth" : 9,
    "size_check" : true,
    "source_list" : [
    ],
    "source_seed" : -1,
    "source_type" : "random2",
    "source_vertex" : 0,
    "stream_from_host" : false,
    "subqueue_latency" : 0,
    "sysinfo" : {
        "machine" : "x86_64",
        "nodename" : "ivb108",
        "release" : "3.10.0-327.18.2.el7.x86_64",
        "sysname" : "Linux",
        "version" : "#1 SMP Thu May 12 11:03:55 UTC 2016"
    },
    "tag" : "do_sweep2",
    "time" : "Wed Nov 30 02:55:31 2016\n",
    "top_nodes" : 0,
    "total_time" : 3045.9060668945312,
    "traversal_mode" : "LB_CULL",
    "undirected" : true,
    "userinfo" : {
        "login" : "ypan"
    },
    "write_time" : 0
}