{
    "64bit_SizeT" : false,
    "64bit_Value" : false,
    "64bit_VertexId" : false,
    "algorithm" : "BFS",
    "alpha" : 6,
    "average_duty" : 0,
    "beta" : 6,
    "command_line" : "./bin/test_bfs_8.0_x86_64 market ../../dataset/large/hollywood-2009/hollywood-2009.mtx --src=randomize2 --queue-sizing=6.5 --in-sizing=4 --iteration-num=64 --tag=do_sweep2 --undirected --idempotence --direction-optimized --traversal-mode=LB_CULL --device=0 --do_a=50 --do_b=500 --jsondir=./eval/CentOS7.2_k40cx1",
    "communicate_latency" : 0,
    "communicate_multipy" : -1,
    "compensate" : false,
    "compiler" : "Gnu GCC C/C++",
    "compiler_version" : 40800005,
    "dataset" : "hollywood-2009",
    "debug_mode" : false,
    "delta" : 0.85000002384185791,
    "delta_factor" : 16,
    "destination_vertex" : 1139904,
    "device_list" : [
        0
    ],
    "direction_optimized" : true,
    "do_a" : 50,
    "do_b" : 500,
    "duplicate_graph" : false,
    "edge_value" : false,
    "edges_queued" : 61129957,
    "edges_redundance" : 0,
    "edges_visited" : 112613306,
    "elapsed" : 11.830110549926758,
    "engine" : "Gunrock",
    "error" : 0.0099999997764825821,
    "expand_latency" : 0,
    "fullqueue_latency" : 0,
    "git_commit_sha1" : "6b7b3e5fddb95feda52dfa83992c51a8e4c14663",
    "gpuinfo" : {
        "clock_rate" : 745000,
        "compute_version" : 35,
        "driver_api" : 8000,
        "driver_version" : 8000,
        "major" : 3,
        "minor" : 5,
        "multi_processor_count" : 15,
        "name" : "Tesla K40m",
        "runtime_version" : 8000,
        "total_global_mem" : 11995578368
    },
    "graph_type" : "market",
    "gunrock_version" : "0.4.0",
    "idempotent" : true,
    "instrument" : false,
    "json" : false,
    "jsondir" : "./eval/CentOS7.2_k40cx1",
    "jsonfile" : "",
    "label" : "",
    "load_time" : 1028.9077758789062,
    "m_teps" : 9519.2099609375,
    "makeout_latency" : 0,
    "mark_predecessors" : false,
    "max_grid_size" : 0,
    "max_in_sizing" : 4,
    "max_iteration" : 50,
    "max_process_time" : 16.21699333190918,
    "max_queue_sizing" : 6.5,
    "max_queue_sizing1" : -1,
    "min_process_time" : 0.15711784362792969,
    "multi_graphs" : false,
    "node_value" : false,
    "nodes_queued" : 786930,
    "nodes_redundance" : 0,
    "nodes_visited" : 1069126,
    "normalized" : false,
    "num_edges" : 112751422,
    "num_gpus" : 1,
    "num_iteration" : 64,
    "num_vertices" : 1139905,
    "output_filename" : "",
    "partition_factor" : -1,
    "partition_method" : "random",
    "partition_seed" : -1,
    "postprocess_time" : 10.663986206054688,
    "preprocess_time" : 606.84084892272949,
    "process_times" : [
        11.310815811157227,
        12.981176376342773,
        10.916948318481445,
        14.257192611694336,
        16.21699333190918,
        16.166925430297852,
        9.5870494842529297,
        9.8111629486083984,
        15.130996704101562,
        12.205123901367188,
        15.183925628662109,
        0.17595291137695312,
        9.7520351409912109,
        11.813879013061523,
        14.64390754699707,
        14.137983322143555,
        16.021013259887695,
        15.655040740966797,
        15.626907348632812,
        8.0831050872802734,
        9.3059539794921875,
        7.9081058502197266,
        8.5999965667724609,
        13.569116592407227,
        13.349056243896484,
        13.856887817382812,
        10.81395149230957,
        15.468120574951172,
        7.6529979705810547,
        11.255979537963867,
        13.905048370361328,
        16.07513427734375,
        8.2910060882568359,
        13.473033905029297,
        15.798091888427734,
        7.8520774841308594,
        15.573978424072266,
        9.4859600067138672,
        9.9399089813232422,
        9.0000629425048828,
        10.275125503540039,
        8.5330009460449219,
        13.818025588989258,
        15.006065368652344,
        8.8601112365722656,
        0.15711784362792969,
        7.9967975616455078,
        7.9150199890136719,
        12.212991714477539,
        12.321949005126953,
        13.319969177246094,
        16.145944595336914,
        11.215925216674805,
        14.245986938476562,
        9.6421241760253906,
        10.490894317626953,
        7.8961849212646484,
        14.572858810424805,
        16.108036041259766,
        10.193109512329102,
        15.379905700683594,
        14.285087585449219,
        15.036106109619141,
        10.64610481262207
    ],
    "quick_mode" : false,
    "quiet_mode" : false,
    "random_edge_value" : false,
    "ref_filename" : "",
    "scaled" : false,
    "search_depth" : 9,
    "size_check" : true,
    "source_list" : [
    ],
    "source_seed" : -1,
    "source_type" : "random2",
    "source_vertex" : 0,
    "stream_from_host" : false,
    "subqueue_latency" : 0,
    "sysinfo" : {
        "machine" : "x86_64",
        "nodename" : "ivb108",
        "release" : "3.10.0-327.18.2.el7.x86_64",
        "sysname" : "Linux",
        "version" : "#1 SMP Thu May 12 11:03:55 UTC 2016"
    },
    "tag" : "do_sweep2",
    "time" : "Wed Nov 30 02:46:42 2016\n",
    "top_nodes" : 0,
    "total_time" : 2776.7128944396973,
    "traversal_mode" : "LB_CULL",
    "undirected" : true,
    "userinfo" : {
        "login" : "ypan"
    },
    "write_time" : 0
}