{
    "64bit_SizeT" : false,
    "64bit_Value" : false,
    "64bit_VertexId" : false,
    "algorithm" : "BFS",
    "alpha" : 6,
    "average_duty" : 0,
    "beta" : 6,
    "command_line" : "./bin/test_bfs_8.0_x86_64 grmat --rmat_scale=22 --rmat_edgefactor=64 --src=randomize2 --queue-sizing=6.5 --in-sizing=4 --iteration-num=64 --tag=do_sweep2 --undirected --idempotence --direction-optimized --traversal-mode=LB_CULL --device=0 --do_a=100 --do_b=10000 --jsondir=./eval/CentOS7.2_k40cx1",
    "communicate_latency" : 0,
    "communicate_multipy" : -1,
    "compensate" : false,
    "compiler" : "Gnu GCC C/C++",
    "compiler_version" : 40800005,
    "dataset" : "rmat_n22_e64",
    "debug_mode" : false,
    "delta" : 0.85000002384185791,
    "delta_factor" : 16,
    "destination_vertex" : 4194303,
    "device_list" : [
        0
    ],
    "direction_optimized" : true,
    "do_a" : 100,
    "do_b" : 10000,
    "duplicate_graph" : false,
    "edge_value" : false,
    "edges_queued" : 117478490,
    "edges_redundance" : 0,
    "edges_visited" : 484093040,
    "elapsed" : 48.354343414306641,
    "engine" : "Gunrock",
    "error" : 0.0099999997764825821,
    "expand_latency" : 0,
    "fullqueue_latency" : 0,
    "git_commit_sha1" : "6b7b3e5fddb95feda52dfa83992c51a8e4c14663",
    "gpuinfo" : {
        "clock_rate" : 745000,
        "compute_version" : 35,
        "driver_api" : 8000,
        "driver_version" : 8000,
        "major" : 3,
        "minor" : 5,
        "multi_processor_count" : 15,
        "name" : "Tesla K40m",
        "runtime_version" : 8000,
        "total_global_mem" : 11995578368
    },
    "graph_type" : "grmat",
    "gunrock_version" : "0.4.0",
    "idempotent" : true,
    "instrument" : false,
    "json" : false,
    "jsondir" : "./eval/CentOS7.2_k40cx1",
    "jsonfile" : "",
    "label" : "",
    "load_time" : 22063.246011734009,
    "m_teps" : 10011.3662109375,
    "makeout_latency" : 0,
    "mark_predecessors" : false,
    "max_grid_size" : 0,
    "max_in_sizing" : 4,
    "max_iteration" : 50,
    "max_process_time" : 72.306156158447266,
    "max_queue_sizing" : 6.5,
    "max_queue_sizing1" : -1,
    "min_process_time" : 18.280982971191406,
    "multi_graphs" : false,
    "node_value" : false,
    "nodes_queued" : 2265450,
    "nodes_redundance" : 0,
    "nodes_visited" : 3108493,
    "normalized" : false,
    "num_edges" : 484093234,
    "num_gpus" : 1,
    "num_iteration" : 64,
    "num_vertices" : 4194304,
    "output_filename" : "",
    "partition_factor" : -1,
    "partition_method" : "random",
    "partition_seed" : -1,
    "postprocess_time" : 25.727987289428711,
    "preprocess_time" : 2463.0000591278076,
    "process_times" : [
        34.624814987182617,
        48.056840896606445,
        53.122997283935547,
        29.394149780273438,
        25.804996490478516,
        42.79017448425293,
        42.270183563232422,
        70.445060729980469,
        22.545099258422852,
        23.49400520324707,
        24.869918823242188,
        53.081989288330078,
        60.065031051635742,
        20.385980606079102,
        55.901050567626953,
        70.142984390258789,
        61.622858047485352,
        56.966066360473633,
        62.072038650512695,
        61.210870742797852,
        69.890975952148438,
        72.306156158447266,
        49.219131469726562,
        71.573972702026367,
        22.653102874755859,
        66.070079803466797,
        65.150976181030273,
        26.790857315063477,
        18.280982971191406,
        46.700000762939453,
        31.485080718994141,
        70.994853973388672,
        22.711992263793945,
        62.044143676757812,
        46.780109405517578,
        70.414066314697266,
        48.959016799926758,
        47.738075256347656,
        54.358005523681641,
        51.132917404174805,
        70.828914642333984,
        34.471035003662109,
        57.275056838989258,
        65.209865570068359,
        44.011116027832031,
        62.628984451293945,
        59.174060821533203,
        25.644063949584961,
        58.920860290527344,
        70.275068283081055,
        65.53196907043457,
        47.318935394287109,
        62.321901321411133,
        34.444808959960938,
        46.670913696289062,
        45.006036758422852,
        55.617094039916992,
        22.630929946899414,
        69.795846939086914,
        23.714780807495117,
        22.614002227783203,
        47.91712760925293,
        50.130844116210938,
        18.402099609375
    ],
    "quick_mode" : false,
    "quiet_mode" : false,
    "random_edge_value" : false,
    "ref_filename" : "",
    "rmat_a" : 0.56999999999999995,
    "rmat_b" : 0.19,
    "rmat_c" : 0.19,
    "rmat_d" : 0.050000000000000044,
    "rmat_edgefactor" : 64,
    "rmat_edges" : 268435456,
    "rmat_nodes" : 4194304,
    "rmat_scale" : 22,
    "rmat_seed" : -1,
    "rmat_vmin" : 1,
    "rmat_vmultipiler" : 64,
    "scaled" : false,
    "search_depth" : 6,
    "size_check" : true,
    "source_list" : [
    ],
    "source_seed" : -1,
    "source_type" : "random2",
    "source_vertex" : 0,
    "stream_from_host" : false,
    "subqueue_latency" : 0,
    "sysinfo" : {
        "machine" : "x86_64",
        "nodename" : "ivb108",
        "release" : "3.10.0-327.18.2.el7.x86_64",
        "sysname" : "Linux",
        "version" : "#1 SMP Thu May 12 11:03:55 UTC 2016"
    },
    "tag" : "do_sweep2",
    "time" : "Wed Nov 30 09:23:35 2016\n",
    "top_nodes" : 0,
    "total_time" : 29340.796947479248,
    "traversal_mode" : "LB_CULL",
    "undirected" : true,
    "userinfo" : {
        "login" : "ypan"
    },
    "write_time" : 0
}